ax520tool.py
ax520tool-0.1.1a0.dist-info/LICENSE
ax520tool-0.1.1a0.dist-info/METADATA
ax520tool-0.1.1a0.dist-info/WHEEL
ax520tool-0.1.1a0.dist-info/entry_points.txt
ax520tool-0.1.1a0.dist-info/top_level.txt
ax520tool-0.1.1a0.dist-info/RECORD
