Metadata-Version: 2.1
Name: ax520tool
Version: 0.1.1a0
Summary: Fully pythonic flash programmer tool for Axera AX520
Home-page: https://github.com/m5stack/ax520tool
Author: Xiao Han
Author-email: hansh-sz@hotmail.com
Classifier: Programming Language :: Python :: 3
Classifier: License :: OSI Approved :: GNU General Public License v3 (GPLv3)
Classifier: Operating System :: OS Independent
Requires-Python: >=3.6
License-File: LICENSE
Requires-Dist: pyserial
Requires-Dist: tqdm
